infra_logging_package/__init__.py
infra_logging_package/logger_manager.py
yan_infra_logging-0.3.3.dist-info/LICENSE
yan_infra_logging-0.3.3.dist-info/METADATA
yan_infra_logging-0.3.3.dist-info/WHEEL
yan_infra_logging-0.3.3.dist-info/top_level.txt
yan_infra_logging-0.3.3.dist-info/RECORD
